plasma/__init__.py
plasma_engine-0.0.1.dist-info/LICENSE
plasma_engine-0.0.1.dist-info/METADATA
plasma_engine-0.0.1.dist-info/WHEEL
plasma_engine-0.0.1.dist-info/top_level.txt
plasma_engine-0.0.1.dist-info/RECORD
