Metadata-Version: 2.1
Name: plasma-engine
Version: 0.0.1
Summary: A pygame-ce-based engine for rapid game development.
Author-email: Matiiss <matiiss@matiiss.com>
Project-URL: Homepage, https://github.com/Matiiss/plasma-engine
Project-URL: Bug Tracker, https://github.com/Matiiss/plasma-engine/issues
Classifier: Programming Language :: Python :: 3
Classifier: License :: OSI Approved :: MIT License
Classifier: Operating System :: OS Independent
Requires-Python: >=3.10
License-File: LICENSE
